skretrieval/__init__.py
skretrieval/_version.py
skretrieval/util.py
skretrieval/core/__init__.py
skretrieval/core/lineshape.py
skretrieval/core/radianceformat.py
skretrieval/core/sasktranformat.py
skretrieval/core/platform/__init__.py
skretrieval/core/platform/balloon.py
skretrieval/core/platform/satellite.py
skretrieval/core/sensor/__init__.py
skretrieval/core/sensor/spectrograph.py
skretrieval/geodetic/__init__.py
skretrieval/legacy/__init__.py
skretrieval/legacy/util.py
skretrieval/legacy/core/simulator.py
skretrieval/legacy/core/sensor/__init__.py
skretrieval/legacy/core/sensor/imager.py
skretrieval/legacy/core/sensor/pixel.py
skretrieval/legacy/core/sensor/spectrograph.py
skretrieval/legacy/retrieval/__init__.py
skretrieval/legacy/retrieval/ozone.py
skretrieval/legacy/retrieval/statevector/__init__.py
skretrieval/legacy/retrieval/statevector/aerosol.py
skretrieval/legacy/retrieval/statevector/profile.py
skretrieval/legacy/sasktran_ext/__init__.py
skretrieval/legacy/sasktran_ext/opticalproperty.py
skretrieval/legacy/tomography/__init__.py
skretrieval/legacy/tomography/grids.py
skretrieval/legacy/tomography/target.py
skretrieval/legacy/tomography/sasktran_ext/__init__.py
skretrieval/legacy/tomography/sasktran_ext/climatology.py
skretrieval/legacy/tomography/sasktran_ext/engine.py
skretrieval/legacy/tomography/sasktran_ext/opticalproperty.py
skretrieval/plotting/__init__.py
skretrieval/retrieval/__init__.py
skretrieval/retrieval/ancillary.py
skretrieval/retrieval/erroranalysis.py
skretrieval/retrieval/forwardmodel.py
skretrieval/retrieval/observation.py
skretrieval/retrieval/prior.py
skretrieval/retrieval/processing.py
skretrieval/retrieval/rodgers.py
skretrieval/retrieval/scipy.py
skretrieval/retrieval/tikhonov.py
skretrieval/retrieval/measvec/__init__.py
skretrieval/retrieval/statevector/__init__.py
skretrieval/retrieval/statevector/altitude.py
skretrieval/retrieval/statevector/constituent.py
skretrieval/retrieval/statevector/shifts.py
skretrieval-2025.6.0.dist-info/METADATA
skretrieval-2025.6.0.dist-info/WHEEL
skretrieval-2025.6.0.dist-info/top_level.txt
skretrieval-2025.6.0.dist-info/RECORD
