Metadata-Version: 2.4
Name: skretrieval
Version: 2025.6.0
Summary: The University of Saskatchewan Retrieval Framework
Author-email: Daniel Zawada <daniel.zawada@usask.ca>
License: MIT
Classifier: Development Status :: 4 - Beta
Classifier: License :: OSI Approved :: MIT License
Classifier: Programming Language :: Python :: 3 :: Only
Classifier: Programming Language :: Python :: 3.11
Classifier: Programming Language :: Python :: 3.12
Classifier: Programming Language :: Python :: 3.13
Requires-Python: >=3.11
Requires-Dist: numpy
Requires-Dist: xarray
Requires-Dist: scipy
Requires-Dist: numba
Requires-Dist: jdcal
Requires-Dist: astropy
Requires-Dist: sasktran2>=2025.5.2
Requires-Dist: simpleeval
Provides-Extra: test
Requires-Dist: pytest; extra == "test"
Provides-Extra: legacy
Requires-Dist: sasktran; extra == "legacy"
Provides-Extra: plotting
Requires-Dist: matplotlib; extra == "plotting"
